eless/__init__.py
eless/auto_config.py
eless/cli.py
eless/config_templates.py
eless/demo_data.py
eless/eless_pipeline.py
eless/health_check.py
eless/interactive_mode.py
eless/tutorial_mode.py
eless/core/__init__.py
eless/core/archiver.py
eless/core/cache_manager.py
eless/core/config_loader.py
eless/core/config_wizard.py
eless/core/default_config.py
eless/core/error_handler.py
eless/core/logging_config.py
eless/core/resource_monitor.py
eless/core/state_manager.py
eless/database/cassandra_connector.py
eless/database/chroma_connector.py
eless/database/db_connector_base.py
eless/database/db_loader.py
eless/database/faiss_connector.py
eless/database/postgresql_connector.py
eless/database/qdrant_connector.py
eless/embedding/embedder.py
eless/embedding/model_loader.py
eless/processing/__init__.py
eless/processing/dispatcher.py
eless/processing/file_scanner.py
eless/processing/parallel_processor.py
eless/processing/streaming_processor.py
eless/processing/parsers/__init__.py
eless/processing/parsers/html_parser.py
eless/processing/parsers/office_parser.py
eless/processing/parsers/pdf_parser.py
eless/processing/parsers/table_parser.py
eless/processing/parsers/text_chunker.py
eless-1.0.0.dist-info/METADATA
eless-1.0.0.dist-info/WHEEL
eless-1.0.0.dist-info/entry_points.txt
eless-1.0.0.dist-info/top_level.txt
eless-1.0.0.dist-info/RECORD
