Metadata-Version: 2.4
Name: eless
Version: 1.0.0
Summary: Evolving Low-resource Embedding and Storage System - A resilient RAG data processing pipeline with comprehensive logging, multi-database support, and CLI interface.
Author: ELESS Team
Author-email: Bandalaro <bandalaro@users.noreply.github.com>
Maintainer-email: Bandalaro <bandalaro@users.noreply.github.com>
License: MIT
Project-URL: Homepage, https://github.com/Bandalaro/eless
Project-URL: Documentation, https://github.com/Bandalaro/eless/tree/main/docs
Project-URL: Repository, https://github.com/Bandalaro/eless.git
Project-URL: Bug Tracker, https://github.com/Bandalaro/eless/issues
Project-URL: Changelog, https://github.com/Bandalaro/eless/blob/main/CHANGELOG.md
Project-URL: Source Code, https://github.com/Bandalaro/eless
Keywords: rag,embedding,vector-database,nlp,ai,document-processing
Classifier: Development Status :: 4 - Beta
Classifier: Intended Audience :: Developers
Classifier: Intended Audience :: Science/Research
Classifier: License :: OSI Approved :: MIT License
Classifier: Operating System :: OS Independent
Classifier: Programming Language :: Python :: 3
Classifier: Programming Language :: Python :: 3.8
Classifier: Programming Language :: Python :: 3.9
Classifier: Programming Language :: Python :: 3.10
Classifier: Programming Language :: Python :: 3.11
Classifier: Programming Language :: Python :: 3.12
Classifier: Topic :: Scientific/Engineering :: Artificial Intelligence
Classifier: Topic :: Text Processing
Classifier: Topic :: Database
Requires-Python: >=3.8
Requires-Dist: click>=8.0.0
Requires-Dist: PyYAML>=6.0
Requires-Dist: numpy>=1.21.0
Requires-Dist: psutil>=5.8.0
Requires-Dist: sentence-transformers>=2.2.0
Provides-Extra: embeddings
Requires-Dist: sentence-transformers>=2.2.0; extra == "embeddings"
Requires-Dist: torch>=1.9.0; extra == "embeddings"
Provides-Extra: databases
Requires-Dist: chromadb>=0.4.0; extra == "databases"
Requires-Dist: langchain-community>=0.0.10; extra == "databases"
Requires-Dist: langchain-core>=0.1.0; extra == "databases"
Requires-Dist: qdrant-client>=1.6.0; extra == "databases"
Requires-Dist: faiss-cpu>=1.7.0; extra == "databases"
Requires-Dist: psycopg2-binary>=2.9.0; extra == "databases"
Requires-Dist: cassandra-driver>=3.28.0; extra == "databases"
Provides-Extra: parsers
Requires-Dist: pypdf>=3.17.0; extra == "parsers"
Requires-Dist: python-docx>=0.8.11; extra == "parsers"
Requires-Dist: openpyxl>=3.1.0; extra == "parsers"
Requires-Dist: pandas>=1.5.0; extra == "parsers"
Requires-Dist: beautifulsoup4>=4.11.0; extra == "parsers"
Requires-Dist: lxml>=4.9.0; extra == "parsers"
Provides-Extra: full
Requires-Dist: sentence-transformers>=2.2.0; extra == "full"
Requires-Dist: torch>=1.9.0; extra == "full"
Requires-Dist: chromadb>=0.4.0; extra == "full"
Requires-Dist: langchain-community>=0.0.10; extra == "full"
Requires-Dist: langchain-core>=0.1.0; extra == "full"
Requires-Dist: qdrant-client>=1.6.0; extra == "full"
Requires-Dist: faiss-cpu>=1.7.0; extra == "full"
Requires-Dist: psycopg2-binary>=2.9.0; extra == "full"
Requires-Dist: cassandra-driver>=3.28.0; extra == "full"
Requires-Dist: pypdf>=3.17.0; extra == "full"
Requires-Dist: python-docx>=0.8.11; extra == "full"
Requires-Dist: openpyxl>=3.1.0; extra == "full"
Requires-Dist: pandas>=1.5.0; extra == "full"
Requires-Dist: beautifulsoup4>=4.11.0; extra == "full"
Requires-Dist: lxml>=4.9.0; extra == "full"
Provides-Extra: dev
Requires-Dist: pytest>=7.0.0; extra == "dev"
Requires-Dist: black>=22.0.0; extra == "dev"
Requires-Dist: flake8>=5.0.0; extra == "dev"
Requires-Dist: mypy>=0.991; extra == "dev"
Requires-Dist: pre-commit>=2.20.0; extra == "dev"
Dynamic: author
Dynamic: requires-python
